docs/.nojekyll
docs/index.html
docs/doctrees/develop-install.doctree
docs/doctrees/environment.pickle
docs/doctrees/index.doctree
docs/doctrees/installing.doctree
docs/doctrees/introduction.doctree
docs/doctrees/modules.doctree
docs/doctrees/setup.doctree
docs/doctrees/trident_chemwidgets.doctree
docs/doctrees/trident_chemwidgets.tests.doctree
docs/doctrees/trident_chemwidgets.widgets.doctree
docs/doctrees/examples/Histogram_widget.doctree
docs/doctrees/examples/InteractiveMolecule_widget.doctree
docs/doctrees/examples/JSME_widget.doctree
docs/doctrees/examples/Scatter_widget.doctree
docs/doctrees/examples/index.doctree
docs/doctrees/nbsphinx/examples/Histogram_widget.ipynb
docs/doctrees/nbsphinx/examples/InteractiveMolecule_widget.ipynb
docs/doctrees/nbsphinx/examples/JSME_widget.ipynb
docs/doctrees/nbsphinx/examples/Scatter_widget.ipynb
docs/doctrees/widgets/Histogram.doctree
docs/doctrees/widgets/InteractiveMolecule.doctree
docs/doctrees/widgets/JSME.doctree
docs/doctrees/widgets/Scatter.doctree
docs/doctrees/widgets/index.doctree
docs/html/.buildinfo
docs/html/develop-install.html
docs/html/genindex.html
docs/html/index.html
docs/html/installing.html
docs/html/introduction.html
docs/html/modules.html
docs/html/objects.inv
docs/html/py-modindex.html
docs/html/search.html
docs/html/searchindex.js
docs/html/setup.html
docs/html/trident_chemwidgets.html
docs/html/trident_chemwidgets.tests.html
docs/html/trident_chemwidgets.widgets.html
docs/html/.doctrees/develop-install.doctree
docs/html/.doctrees/environment.pickle
docs/html/.doctrees/index.doctree
docs/html/.doctrees/installing.doctree
docs/html/.doctrees/introduction.doctree
docs/html/.doctrees/modules.doctree
docs/html/.doctrees/setup.doctree
docs/html/.doctrees/trident_chemwidgets.doctree
docs/html/.doctrees/trident_chemwidgets.tests.doctree
docs/html/.doctrees/trident_chemwidgets.widgets.doctree
docs/html/.doctrees/examples/Histogram_widget.doctree
src/trident_chemwidgets.egg-info/PKG-INFO
src/trident_chemwidgets.egg-info/SOURCES.txt
src/trident_chemwidgets.egg-info/dependency_links.txt
src/trident_chemwidgets.egg-info/requires.txt
src/trident_chemwidgets.egg-info/top_level.txt
trident_chemwidgets-0.2.1.dist-info/LICENSE.txt
trident_chemwidgets-0.2.1.dist-info/METADATA
trident_chemwidgets-0.2.1.dist-info/WHEEL
trident_chemwidgets-0.2.1.dist-info/top_level.txt
trident_chemwidgets-0.2.1.dist-info/RECORD
