Metadata-Version: 2.1
Name: trident-chemwidgets
Version: 0.2.1
Summary: Jupyter widgets for working with chemical datasets
Home-page: https://github.com/tridentbio/trident-chemwidgets
Author: Trident Bioscience, Inc.
Author-email: info@trident.bio
Maintainer: Tyler Shimko
Maintainer-email: tshimko@trident.bio
Keywords: Jupyter,Widgets,IPython,Chemistry,Visualization
Platform: Linux
Platform: Mac OS X
Platform: Windows
Classifier: Intended Audience :: Developers
Classifier: Intended Audience :: Science/Research
Classifier: License :: OSI Approved :: BSD License
Classifier: Programming Language :: Python
Classifier: Programming Language :: Python :: 3
Classifier: Programming Language :: Python :: 3.8
Classifier: Programming Language :: Python :: 3.9
Classifier: Programming Language :: Python :: 3.10
Classifier: Framework :: Jupyter
Requires-Python: >=3.8
License-File: LICENSE.txt
Requires-Dist: ipywidgets (>=7.0.0)
Requires-Dist: pandas (>=1.0.0)
Provides-Extra: docs
Requires-Dist: jupyter-sphinx ; extra == 'docs'
Requires-Dist: myst-parser ; extra == 'docs'
Requires-Dist: nbsphinx ; extra == 'docs'
Requires-Dist: nbsphinx-link ; extra == 'docs'
Requires-Dist: pytest-check-links ; extra == 'docs'
Requires-Dist: pypandoc ; extra == 'docs'
Requires-Dist: recommonmark ; extra == 'docs'
Requires-Dist: sphinx (>=1.5) ; extra == 'docs'
Requires-Dist: sphinx-autobuild ; extra == 'docs'
Requires-Dist: sphinx-rtd-theme ; extra == 'docs'
Requires-Dist: furo ; extra == 'docs'
Provides-Extra: test
Requires-Dist: pytest (>=4.6) ; extra == 'test'
Requires-Dist: pytest-cov ; extra == 'test'
Requires-Dist: nbval ; extra == 'test'
